foliate/__init__.py
foliate/__main__.py
foliate/assets.py
foliate/build.py
foliate/cache.py
foliate/cli.py
foliate/config.py
foliate/defaults/__init__.py
foliate/defaults/config.toml
foliate/defaults/static/__init__.py
foliate/defaults/static/main.css
foliate/defaults/templates/__init__.py
foliate/defaults/templates/feed.xml
foliate/defaults/templates/index.html
foliate/defaults/templates/layout.html
foliate/defaults/templates/page.html
foliate/deploy.py
foliate/feed.py
foliate/logging.py
foliate/markdown_utils.py
foliate/obsidian_image_size.py
foliate/postprocess.py
foliate/quarto.py
foliate/resources.py
foliate/templates.py
foliate/watch.py
foliate-0.3.1.dist-info/WHEEL
foliate-0.3.1.dist-info/entry_points.txt
foliate-0.3.1.dist-info/METADATA
foliate-0.3.1.dist-info/RECORD
