Metadata-Version: 2.4
Name: foliate
Version: 0.3.1
Summary: Minimal static site generator for markdown vaults
Keywords: static-site-generator,markdown,wiki,obsidian
Author: YY Ahn
License-Expression: MIT
Classifier: Development Status :: 3 - Alpha
Classifier: Environment :: Console
Classifier: Intended Audience :: Developers
Classifier: Intended Audience :: End Users/Desktop
Classifier: License :: OSI Approved :: MIT License
Classifier: Operating System :: OS Independent
Classifier: Programming Language :: Python :: 3
Classifier: Programming Language :: Python :: 3.12
Classifier: Programming Language :: Python :: 3.13
Classifier: Topic :: Internet :: WWW/HTTP :: Site Management
Classifier: Topic :: Text Processing :: Markup :: Markdown
Requires-Dist: python-frontmatter>=1.0.0
Requires-Dist: markdown>=3.4
Requires-Dist: jinja2>=3.1
Requires-Dist: click>=8.0
Requires-Dist: watchdog>=3.0
Requires-Dist: pygments>=2.15
Requires-Dist: markdown-katex>=202406.1035
Requires-Dist: mdx-wikilink-plus>=1.4
Requires-Dist: mdx-linkify>=2.1
Requires-Dist: beautifulsoup4>=4.12
Requires-Dist: pytest>=7.0 ; extra == 'dev'
Requires-Dist: pytest-cov>=4.0 ; extra == 'dev'
Requires-Dist: ruff>=0.1 ; extra == 'dev'
Requires-Dist: quarto-prerender>=0.1 ; extra == 'quarto'
Requires-Python: >=3.12
Project-URL: Homepage, https://github.com/yy/foliate
Project-URL: Issues, https://github.com/yy/foliate/issues
Project-URL: Repository, https://github.com/yy/foliate
Provides-Extra: dev
Provides-Extra: quarto
